FourStagePipelining/pipeline.v
module pipeline(
	output [15:0] C, 
	input [3:0] ra1,	/*Register read address 1*/
	input [3:0] ra2,	/*Register read address 2*/
	input [3:0] rwa,	/*Register write address*/
	input [7:0] ma,		/*Memory write address*/
	input [3:0] func,	/*Operation to be executed*/
	input clk1,			/*Two phase clock*/
	input clk2);

	reg [15:0] L12_A, L12_B, L23_C, L34_C;
	reg [3:0] L12_rwa, L12_func, L23_rwa;
	reg [7:0] L12_ma, L23_ma, L34_ma;

	reg [15:0] regbank [0:15]; /*16x16 Register Bank*/
	reg [15:0] mem [0:255]; /*256x16 Memory*/

	assign C = L34_C;

	always @ (posedge clk1)			/*Stage 1*/
	begin
		L12_A 		<= #2 regbank[ra1];
		L12_B 		<= #2 regbank[ra2];
		L12_rwa 	<= #2 rwa;
		L12_func 	<= #2 func;
		L12_ma 		<= #2 ma;
	end

	always @ (negedge clk2)			/*Stage 2*/
	begin
		case(L12_func)
			4'b0000: #2 L23_C <= L12_A + L12_B;
			4'b0001: #2 L23_C <= L12_A - L12_B;
			4'b0010: #2 L23_C <= L12_A * L12_B;
			4'b0011: #2 L23_C <= L12_A; 		/*Select A*/
			4'b0100: #2 L23_C <= L12_B; 		/*Select B*/
			4'b0101: #2 L23_C <= L12_A & L12_B;
			4'b0110: #2 L23_C <= L12_A | L12_B;
			4'b0111: #2 L23_C <= L12_A ^ L12_B;
			4'b1000: #2 L23_C <= L12_A ~^ L12_B;
			4'b1001: #2 L23_C <= ~L12_A;
			4'b1010: #2 L23_C <= ~L12_B;
			4'b1011: #2 L23_C <= L12_A >> 1;
			4'b1100: #2 L23_C <= L12_A << 1;
			default: #2 L23_C <= 16'hxxxx;
		endcase
		L23_ma <= #2 L12_ma;
		L23_rwa <= #2 L12_rwa;
	end

	always @ (posedge clk1)			/*Stage 3*/
	begin
		regbank[L23_rwa] 	<= #2 L23_C;
		L34_ma 				<= #2 L23_ma;
		L34_C 				<= #2 L23_C;
	end

	always @ (negedge clk2)			/*Stage 4*/
	begin
		mem[L34_ma] <= #2 L34_C; 
	end

endmodule

FourStagePipelining/pipeline_testbench.v
module pipeline_testbench();

reg clk1,clk2;
reg [3:0] ra1,ra2,func,rwa;
reg [7:0] ma;

wire [15:0] C;
integer i;

pipeline p1(C,ra1,ra2,rwa,ma,func,clk1,clk2);

initial
begin
	clk1 = 1'b0; clk2 = 1'b0;

	repeat(30)			/*Generating two phase clock*/
	begin
		clk1 = #5 1'b1; clk1 = #5 1'b0;
		clk2 = #5 1'b1; clk2 = #5 1'b0;
	end
end

initial
begin
	for(i=0;i<15;i=i+1)			/*Initializing regbank*/
		p1.regbank[i] = i*i;
end

initial
begin
	#5 ra1 = 2; ra2 = 7; func = 0; rwa =12; ma = 145;
	#20 ra1 = 1; ra2 = 4; func = 4; rwa =13; ma = 169;
	#20 ra1 = 9; ra2 = 5; func = 3; rwa =11; ma = 132;
	#20 ra1 = 6; ra2 = 2; func = 7; rwa =14; ma = 140;

	#50
	for(i=132; i<170; i = i+1)
		$display("Memory[%3d] = %d", i, p1.mem[i]);
end

initial
begin
	$dumpfile("pipeline.vcd");
	$dumpvars(0,pipeline_testbench);
	$monitor($time,"Output = %d",C);
	#200 $finish;
end

endmodule

FourStagePipelining/pipeline.vcd
$date
	Tue May 26 10:03:56 2020
$end
$version
	Icarus Verilog
$end
$timescale
	1s
$end
$scope module pipeline_testbench $end
$var wire 16 ! C [15:0] $end
$var reg 1 " clk1 $end
$var reg 1 # clk2 $end
$var reg 4 $ func [3:0] $end
$var reg 8 % ma [7:0] $end
$var reg 4 & ra1 [3:0] $end
$var reg 4 ' ra2 [3:0] $end
$var reg 4 ( rwa [3:0] $end
$var integer 32 ) i [31:0] $end
$scope module p1 $end
$var wire 16 * C [15:0] $end
$var wire 1 " clk1 $end
$var wire 1 # clk2 $end
$var wire 4 + func [3:0] $end
$var wire 8 , ma [7:0] $end
$var wire 4 - ra1 [3:0] $end
$var wire 4 . ra2 [3:0] $end
$var wire 4 / rwa [3:0] $end
$var reg 16 0 L12_A [15:0] $end
$var reg 16 1 L12_B [15:0] $end
$var reg 4 2 L12_func [3:0] $end
$var reg 8 3 L12_ma [7:0] $end
$var reg 4 4 L12_rwa [3:0] $end
$var reg 16 5 L23_C [15:0] $end
$var reg 8 6 L23_ma [7:0] $end
$var reg 4 7 L23_rwa [3:0] $end
$var reg 16 8 L34_C [15:0] $end
$var reg 8 9 L34_ma [7:0] $end
$upscope $end
$upscope $end
$enddefinitions $end
#0
$dumpvars
bx 9
bx 8
bx 7
bx 6
bx 5
bx 4
bx 3
bx 2
bx 1
bx 0
bx /
bx .
bx -
bx ,
bx +
bx *
b1111 )
bx (
bx '
bx &
bx %
bx $
0#
0"
bx !
$end
#5
b10010001 %
b10010001 ,
b1100 (
b1100 /
b0 $
b0 +
b111 '
b111 .
b10 &
b10 -
1"
#7
b10010001 3
b0 2
b1100 4
b110001 1
b100 0
#10
0"
#15
1#
#20
0#
#22
b110101 5
#24
b1100 7
b10010001 6
#25
1"
b10101001 %
b10101001 ,
b1101 (
b1101 /
b100 $
b100 +
b100 '
b100 .
b1 &
b1 -
#27
b110101 !
b110101 *
b110101 8
b10010001 9
b10101001 3
b100 2
b1101 4
b10000 1
b1 0
#30
0"
#35
1#
#40
0#
#42
b10000 5
#44
b1101 7
b10101001 6
#45
1"
b10000100 %
b10000100 ,
b1011 (
b1011 /
b11 $
b11 +
b101 '
b101 .
b1001 &
b1001 -
#47
b10000100 3
b11 2
b1011 4
b11001 1
b1010001 0
b10000 !
b10000 *
b10000 8
b10101001 9
#50
0"
#55
1#
#60
0#
#62
b1010001 5
#64
b1011 7
b10000100 6
#65
1"
b10001100 %
b10001100 ,
b1110 (
b1110 /
b111 $
b111 +
b10 '
b10 .
b110 &
b110 -
#67
b1010001 !
b1010001 *
b1010001 8
b10000100 9
b10001100 3
b111 2
b1110 4
b100 1
b100100 0
#70
0"
#75
1#
#80
0#
#82
b100000 5
#84
b1110 7
b10001100 6
#85
1"
#87
b100000 !
b100000 *
b100000 8
b10001100 9
#90
0"
#95
1#
#100
0#
#105
1"
#110
0"
#115
1#
b10101010 )
