MealyFSM/MealyFSM.v
/*This FSM is detects the pattern 11011*/

module MealyFSM(
	input a, 
	input rst,
	input clk,
	output reg b);

	parameter s0 = 3'b000, s1 = 3'b001, s2 = 3'b010, s3 = 3'b011, s4 = 3'b100;

	reg [2:0] PresentState;
	reg [2:0] NextState;

	always @ (posedge clk)
	begin
		if (rst)
			PresentState <= s0;
		else
			PresentState <= NextState;
	end

	always @ (PresentState,a)
	begin
		case(PresentState)
			s0: if(a) 
				begin
					NextState = s1;
					b = 1'b0;
				end
				else
				begin
					NextState = s0;
					b = 1'b0;
				end		
			s1: if(a) 
				begin
					NextState = s2;
					b = 1'b0;
				end
				else
				begin
					NextState = s0;
					b = 1'b0;
				end		
			s2: if(a) 
					begin
						NextState = s2;
						b = 1'b0;
					end
				else
				begin
					NextState = s3;
					b = 1'b0;
				end		
			s3: if(a) 
				begin
					NextState = s4;
					b = 1'b0;
				end
				else
				begin
					NextState = s0;
					b = 1'b0;
				end		
			s4: if(a) 
				begin
					NextState = s2;
					b = 1'b1;
				end
				else
				begin
					NextState = s0;
					b = 1'b0;
				end		
			default: PresentState = s0;
		endcase
	end
endmodule

MealyFSM/MealyFSM_TestBench.v
module MealyFSM_TestBench();

reg a, rst, clk;
wire b;

MealyFSM m1(a, rst, clk, b);

initial
begin
a = 1'b0;
clk = 1'b0;
rst = 1'b0;
end

always
begin
	#2 clk = ~clk;
end
initial
begin
	#1 rst = 1'b1;
	#5 rst = 1'b0; a = 1'b1;
	#5 a = 1'b1;
	#5 a = 1'b0;
	#5 a = 1'b1;
	#5 a = 1'b0;
	#5 a = 1'b1;
	#5 a = 1'b1;
	#5 a = 1'b0;
	#5 a = 1'b1;
	#5 a = 1'b1;
end

initial 
begin
	$dumpfile("MealyFSM_TestBench.vcd");
	$dumpvars(0, MealyFSM_TestBench);
	$monitor($time,"	Input = %b State = %d Output = %d", a, m1.PresentState, b);
	#200 $finish;
end

endmodule

MealyFSM/MealyFSM_TestBench.vcd
$date
	Thu May 28 22:41:49 2020
$end
$version
	Icarus Verilog
$end
$timescale
	1s
$end
$scope module MealyFSM_TestBench $end
$var wire 1 ! b $end
$var reg 1 " a $end
$var reg 1 # clk $end
$var reg 1 $ rst $end
$scope module m1 $end
$var wire 1 " a $end
$var wire 1 # clk $end
$var wire 1 $ rst $end
$var reg 3 % NextState [2:0] $end
$var reg 3 & PresentState [2:0] $end
$var reg 1 ! b $end
$upscope $end
$upscope $end
$enddefinitions $end
#0
$dumpvars
b0 &
bx %
0$
0#
0"
x!
$end
#1
1$
#2
1#
#4
0#
#6
b1 &
0!
b10 %
1#
1"
0$
#8
0#
#10
b10 &
1#
#12
0#
#14
1#
#16
b11 %
0#
0"
#18
b0 %
b11 &
1#
#20
0#
#21
b100 %
1"
#22
1!
b10 %
b100 &
1#
#24
0#
#26
b0 &
0!
b0 %
1#
0"
#28
0#
#30
1#
#31
b1 %
1"
#32
0#
#34
b10 %
b1 &
1#
#36
0#
#38
b10 &
1#
#40
0#
#41
b11 %
0"
#42
b0 %
b11 &
1#
#44
0#
#46
1!
b100 &
b10 %
1#
1"
#48
0#
#50
0!
b10 &
1#
